gsaphub/__init__.py
gsaphub/_inception_url_helper.py
gsaphub/clients.py
gsaphub/env.py
gsaphub/labels.py
gsaphub/text_units.py
gsaphub-0.3.0.dist-info/METADATA
gsaphub-0.3.0.dist-info/WHEEL
gsaphub-0.3.0.dist-info/top_level.txt
gsaphub-0.3.0.dist-info/RECORD
